tree_sitter_cg-1.1.2.dist-info/RECORD
tree_sitter_cg-1.1.2.dist-info/top_level.txt
tree_sitter_cg-1.1.2.dist-info/METADATA
tree_sitter_cg-1.1.2.dist-info/WHEEL
tree_sitter_cg/__init__.pyi
tree_sitter_cg/_binding.abi3.so
tree_sitter_cg/py.typed
tree_sitter_cg/binding.c
tree_sitter_cg/__init__.py
tree_sitter_cg/queries/highlights.scm
