Metadata-Version: 2.1
Name: tree-sitter-cg
Version: 1.1.2
Summary: tree-sitter grammar of VISL-CG
Author: Daniel Swanson
License: GPL-3.0-or-later
Project-URL: Homepage, https://github.com/apertium/tree-sitter-apertium
Keywords: incremental,parsing,tree-sitter,cg
Classifier: Intended Audience :: Developers
Classifier: Topic :: Software Development :: Compilers
Classifier: Topic :: Text Processing :: Linguistic
Classifier: Typing :: Typed
Requires-Python: >=3.9
Provides-Extra: core
Requires-Dist: tree-sitter ~=0.22 ; extra == 'core'
